hcalory_control/__init__.py
hcalory_control/heater.py
hcalory_control/py.typed
hcalory_control-0.1.6.dist-info/METADATA
hcalory_control-0.1.6.dist-info/WHEEL
hcalory_control-0.1.6.dist-info/entry_points.txt
hcalory_control-0.1.6.dist-info/licenses/LICENSE
hcalory_control-0.1.6.dist-info/RECORD
