Metadata-Version: 2.4
Name: hcalory-control
Version: 0.1.6
Summary: A tool for controlling Hcalory diesel heaters over Bluetooth.
Project-URL: Repository, https://github.com/evanfoster/hcalory-control
Author-email: Evan Foster <evan@fos.tech>
License-File: LICENSE
Keywords: ble,bluetooth,diesel,hcalory,heater
Classifier: Development Status :: 3 - Alpha
Classifier: Intended Audience :: Developers
Classifier: License :: OSI Approved :: GNU Lesser General Public License v3 or later (LGPLv3+)
Classifier: Programming Language :: Python
Classifier: Programming Language :: Python :: 3 :: Only
Classifier: Programming Language :: Python :: 3.11
Classifier: Programming Language :: Python :: 3.12
Classifier: Programming Language :: Python :: 3.13
Classifier: Topic :: Home Automation
Requires-Python: >=3.11
Requires-Dist: bleak-retry-connector<4.0
Requires-Dist: bleak<1.0.0
Requires-Dist: py-datastruct<3.0.0
